src/contador/contador.v
module contador (
    input  wire       reloj,
    input  wire       reset,
    input  wire       enable,
    input  wire       suma_resta,
    output reg  [3:0] resultado
);

    wire [3:0] suma;

    // suma_resta = 1 -> suma 1
    // suma_resta = 0 -> resta 1
    assign suma = resultado + (suma_resta ? 4'b0001 : 4'b1111);

    always @(posedge reloj, negedge reset) begin
        if (!reset)
            resultado <= 4'b0000;
        else if (enable)
            resultado <= suma;
    end

endmodule

cocotb/tb_contador/tb.v

`timescale 1ns / 1ps

module tb ();

    initial begin
        $dumpfile("dump.vcd");
        $dumpvars(0, tb); // Al apuntar a 'tb', grabará este módulo y todo lo que instancie adentro
        #1;
    end

    reg clk;
    reg rst;
    reg enable;
    reg suma_resta;

    wire [3:0] suma_out;

    contador user_project (
        .reloj         (clk),
        .reset          (rst),
        .enable 		(enable),
        .suma_resta 	(suma_resta),
        .resultado	(suma_out)
    );

endmodule

cocotb/tb_contador/dump.vcd
$date
	Mon Oct  5 23:08:53 2026
$end
$version
	Icarus Verilog
$end
$timescale
	1ps
$end
$scope module tb $end
$var wire 4 ! suma_out [3:0] $end
$var reg 1 " clk $end
$var reg 1 # enable $end
$var reg 1 $ rst $end
$var reg 1 % suma_resta $end
$scope module user_project $end
$var wire 1 # enable $end
$var wire 1 " reloj $end
$var wire 1 $ reset $end
$var wire 1 % suma_resta $end
$var wire 4 & suma [3:0] $end
$var reg 4 ' resultado [3:0] $end
$upscope $end
$upscope $end
$enddefinitions $end
$comment Show the parameter values. $end
$dumpall
$end
#0
$dumpvars
b0 '
b1 &
1%
0$
0#
0"
b0 !
$end
#6000
1"
#11000
0"
#16000
1"
#21000
1$
0"
#26000
1"
#31000
0"
#36000
1"
#41000
0"
#46000
1"
#51000
1#
0"
#56000
b10 &
b1 !
b1 '
1"
#61000
0"
#66000
b11 &
b10 !
b10 '
1"
#71000
0"
#76000
b100 &
b11 !
b11 '
1"
#81000
0"
#86000
b101 &
b100 !
b100 '
1"
#91000
0"
#96000
b110 &
b101 !
b101 '
1"
#101000
0"
#106000
b111 &
b110 !
b110 '
1"
#111000
0"
#116000
b1000 &
b111 !
b111 '
1"
#121000
0"
#126000
b1001 &
b1000 !
b1000 '
1"
#131000
0"
#136000
b1010 &
b1001 !
b1001 '
1"
#141000
0"
#146000
b1011 &
b1010 !
b1010 '
1"
#151000
0"
#156000
b1100 &
b1011 !
b1011 '
1"
#161000
0"
#166000
b1101 &
b1100 !
b1100 '
1"
#171000
0"
#176000
b1110 &
b1101 !
b1101 '
1"
#181000
0"
#186000
b1111 &
b1110 !
b1110 '
1"
#191000
0"
#196000
b0 &
b1111 !
b1111 '
1"
#201000
0"
#206000
b1 &
b0 !
b0 '
1"
#211000
b1111 &
0%
0"
#216000
b1110 &
b1111 !
b1111 '
1"
#221000
0"
#226000
b1101 &
b1110 !
b1110 '
1"
#231000
0"
#236000
b1100 &
b1101 !
b1101 '
1"
#241000
0"
#246000
b1011 &
b1100 !
b1100 '
1"
#251000
0"
#256000
b1010 &
b1011 !
b1011 '
1"
#261000
0"
#266000
b1001 &
b1010 !
b1010 '
1"
#271000
0"
#276000
b1000 &
b1001 !
b1001 '
1"
#281000
0"
#286000
b111 &
b1000 !
b1000 '
1"
#291000
0"
#296000
b110 &
b111 !
b111 '
1"
#301000
0"
#306000
b101 &
b110 !
b110 '
1"
#311000
0"
#316000
b100 &
b101 !
b101 '
1"
#321000
0"
#326000
b11 &
b100 !
b100 '
1"
#331000
0"
#336000
b10 &
b11 !
b11 '
1"
#341000
0"
#346000
b1 &
b10 !
b10 '
1"
#351000
0"
#356000
b0 &
b1 !
b1 '
1"
#361000
0"
#366000
b1111 &
b0 !
b0 '
1"
#371000
0#
0"
#376000
1"
#381000
0"
#386000
1"
#391000
0"
#396000
1"
#401000
b1 &
1%
1#
0"
#406000
b10 &
b1 !
b1 '
1"
#411000
0"
#416000
b11 &
b10 !
b10 '
1"
#421000
0"
#426000
b100 &
b11 !
b11 '
1"
#431000
0"
#436000
b101 &
b100 !
b100 '
1"
#441000
0"
#446000
b110 &
b101 !
b101 '
1"
#451000
b1 &
b0 !
b0 '
0$
0"
